aeclib/__init__.py
aeclib-0.0.1.dist-info/licenses/LICENSE
aeclib-0.0.1.dist-info/METADATA
aeclib-0.0.1.dist-info/WHEEL
aeclib-0.0.1.dist-info/top_level.txt
aeclib-0.0.1.dist-info/RECORD
