Metadata-Version: 2.4
Name: aeclib
Version: 0.0.1
Summary: Open-source computational logic engine for global building codes and standards.
Author-email: Nguyen Ngo <nguyen@aeclib.com>
License-Expression: Apache-2.0
Project-URL: Homepage, https://github.com/aeclib/aeclib
Project-URL: Bug Tracker, https://github.com/aeclib/aeclib/issues
Project-URL: Documentation, https://github.com/aeclib/aeclib#readme
Classifier: Development Status :: 2 - Pre-Alpha
Classifier: Intended Audience :: Developers
Classifier: Intended Audience :: Science/Research
Classifier: Topic :: Scientific/Engineering
Classifier: Programming Language :: Python :: 3
Classifier: Programming Language :: Python :: 3.9
Classifier: Programming Language :: Python :: 3.10
Classifier: Programming Language :: Python :: 3.11
Classifier: Programming Language :: Python :: 3.12
Classifier: Operating System :: OS Independent
Requires-Python: >=3.9
License-File: LICENSE
Dynamic: license-file
